{
  "person": [
{"id":1,"first_name":"Shaylynn","last_name":"Koba","tel":"714-365-2993"},
{"id":2,"first_name":"Orran","last_name":"Pittoli","tel":"511-402-9056"},
{"id":3,"first_name":"Finley","last_name":"Snassell","tel":"210-666-8806"},
{"id":4,"first_name":"Cindra","last_name":"Fuge","tel":"528-257-3977"},
{"id":5,"first_name":"Teressa","last_name":"Mort","tel":"166-480-3040"},
{"id":6,"first_name":"Merridie","last_name":"Scholl","tel":"106-578-3564"},
{"id":7,"first_name":"Ardene","last_name":"Aleksic","tel":"434-989-6251"},
{"id":8,"first_name":"Darell","last_name":"Conelly","tel":"511-673-3541"},
{"id":9,"first_name":"Emmey","last_name":"Pottery","tel":"590-480-0938"},
{"id":10,"first_name":"Weylin","last_name":"Lalonde","tel":"528-938-0997"}],
  "profile": {
    "name": "mrcoco0264"
  }
}
